[
  {
    "id": "log_1774878746024",
    "actionType": "message_replied",
    "messageId": "m_1774878746024",
    "channelId": "c1",
    "performedBy": "Redking",
    "targetAuthor": "Redking",
    "oldContent": null,
    "newContent": "testing",
    "replyTargetId": "m_1774878223158",
    "timestamp": 1774878746024
  },
  {
    "id": "log_1774878762679",
    "actionType": "message_edited",
    "messageId": "m_1774878223158",
    "channelId": "c1",
    "performedBy": "Redking",
    "targetAuthor": "Redking",
    "oldContent": "Test",
    "newContent": "no to",
    "replyTargetId": null,
    "timestamp": 1774878762679
  },
  {
    "id": "log_1774879454027",
    "actionType": "message_deleted",
    "messageId": "m_1774878223158",
    "channelId": "c1",
    "performedBy": "Redking",
    "targetAuthor": "Redking",
    "oldContent": "no to",
    "newContent": "[deleted]",
    "replyTargetId": null,
    "timestamp": 1774879454027
  },
  {
    "id": "log_1774895993464",
    "actionType": "message_sent",
    "messageId": "m_1774895993464",
    "channelId": "c1",
    "performedBy": "Redking",
    "targetAuthor": "Redking",
    "oldContent": null,
    "newContent": "test",
    "replyTargetId": null,
    "timestamp": 1774895993464
  },
  {
    "id": "log_1774946982489",
    "actionType": "message_edited",
    "messageId": "m_1774878746024",
    "channelId": "c1",
    "performedBy": "Unknown",
    "targetAuthor": "Redking",
    "oldContent": "testing",
    "newContent": "A bug",
    "replyTargetId": "m_1774878223158",
    "timestamp": 1774946982489
  },
  {
    "id": "log_1774946990155",
    "actionType": "message_sent",
    "messageId": "m_1774946990155",
    "channelId": "c1",
    "performedBy": "JohnDoe",
    "targetAuthor": "JohnDoe",
    "oldContent": null,
    "newContent": "test",
    "replyTargetId": null,
    "timestamp": 1774946990155
  },
  {
    "id": "log_1774947006627",
    "actionType": "message_edited",
    "messageId": "m_1774946990155",
    "channelId": "c1",
    "performedBy": "Unknown",
    "targetAuthor": "JohnDoe",
    "oldContent": "test",
    "newContent": "yuh",
    "replyTargetId": null,
    "timestamp": 1774947006627
  },
  {
    "id": "log_1774990295870",
    "actionType": "message_edited",
    "messageId": "m_1774990284871",
    "channelId": "c1",
    "performedBy": "REDKING_11",
    "targetAuthor": "REDKING_11",
    "oldContent": "test",
    "newContent": "mayby",
    "replyTargetId": null,
    "timestamp": 1774990295870
  },
  {
    "id": "log_1774990297515",
    "actionType": "message_deleted",
    "messageId": "m_1774990284871",
    "channelId": "c1",
    "performedBy": "REDKING_11",
    "targetAuthor": "REDKING_11",
    "oldContent": "mayby",
    "newContent": "[deleted]",
    "replyTargetId": null,
    "timestamp": 1774990297515
  },
  {
    "id": "log_1775036809187",
    "actionType": "message_deleted",
    "messageId": "m_1774990603080",
    "channelId": "c1",
    "performedBy": "REDKING_11",
    "targetAuthor": "REDKING_11",
    "oldContent": "test",
    "newContent": "[deleted]",
    "replyTargetId": null,
    "timestamp": 1775036809187
  },
  {
    "id": "log_1775038510268",
    "actionType": "message_sent",
    "messageId": "m_1775038510267",
    "channelId": "c1",
    "performedBy": "REDKING_11",
    "targetAuthor": "REDKING_11",
    "oldContent": null,
    "newContent": "test",
    "replyTargetId": null,
    "timestamp": 1775038510268
  },
  {
    "id": "log_1775038516521",
    "actionType": "message_edited",
    "messageId": "m_1775038510267",
    "channelId": "c1",
    "performedBy": "REDKING_11",
    "targetAuthor": "REDKING_11",
    "oldContent": "test",
    "newContent": "testing",
    "replyTargetId": null,
    "timestamp": 1775038516521
  },
  {
    "id": "log_1775038524716",
    "actionType": "message_replied",
    "messageId": "m_1775038524715",
    "channelId": "c1",
    "performedBy": "REDKING_11",
    "targetAuthor": "REDKING_11",
    "oldContent": null,
    "newContent": "yuh",
    "replyTargetId": "m_1775037749610",
    "timestamp": 1775038524716
  },
  {
    "id": "log_1775038529636",
    "actionType": "message_edited",
    "messageId": "m_1775038524715",
    "channelId": "c1",
    "performedBy": "REDKING_11",
    "targetAuthor": "REDKING_11",
    "oldContent": "yuh",
    "newContent": "yuh uh",
    "replyTargetId": "m_1775037749610",
    "timestamp": 1775038529636
  }
]